README.md
setup.cfg
setup.py
graphenize/__init__.py
graphenize/builder.py
graphenize/cli.py
graphenize/model.py
graphenize/registry.py
graphenize/utils.py
graphenize.egg-info/PKG-INFO
graphenize.egg-info/SOURCES.txt
graphenize.egg-info/dependency_links.txt
graphenize.egg-info/entry_points.txt
graphenize.egg-info/requires.txt
graphenize.egg-info/top_level.txt
graphenize.egg-info/zip-safe
graphenize/tests/__init__.py
graphenize/tests/test_builder.py
graphenize/tests/test_utils.py