Metadata-Version: 1.2
Name: graphenize
Version: 0.1.0
Summary: Auto-generation Graphene models from json.
Home-page: https://github.com/abawchen/graphenize
Author: Abaw Chen
Author-email: abaw.chen@gmail.com
License: MIT
Keywords: graphql json rest api graphene schema graphenize
Platform: UNKNOWN
Classifier: Development Status :: 3 - Alpha
Classifier: Intended Audience :: Developers
Classifier: Topic :: Software Development :: Libraries
Classifier: Programming Language :: Python :: 2.7
Classifier: Programming Language :: Python :: 3.3
Classifier: Programming Language :: Python :: 3.4
Classifier: Programming Language :: Python :: 3.5
Classifier: Programming Language :: Python :: 3.6
Classifier: Programming Language :: Python :: Implementation :: PyPy
Requires-Python: >=2.7
